streamlit_toggle/__init__.py
streamlit_toggle/frontend/build/asset-manifest.json
streamlit_toggle/frontend/build/bootstrap.min.css
streamlit_toggle/frontend/build/index.html
streamlit_toggle/frontend/build/precache-manifest.2776bb5194ede4750115f38121622206.js
streamlit_toggle/frontend/build/service-worker.js
streamlit_toggle/frontend/build/static/css/main.9ae38243.chunk.css
streamlit_toggle/frontend/build/static/css/main.9ae38243.chunk.css.map
streamlit_toggle/frontend/build/static/js/2.449282fd.chunk.js
streamlit_toggle/frontend/build/static/js/2.449282fd.chunk.js.LICENSE.txt
streamlit_toggle/frontend/build/static/js/2.449282fd.chunk.js.map
streamlit_toggle/frontend/build/static/js/main.c16910cb.chunk.js
streamlit_toggle/frontend/build/static/js/main.c16910cb.chunk.js.map
streamlit_toggle/frontend/build/static/js/runtime-main.fd5c39a2.js
streamlit_toggle/frontend/build/static/js/runtime-main.fd5c39a2.js.map
streamlit_toggle_switch_aai-4.0.6.dist-info/LICENSE
streamlit_toggle_switch_aai-4.0.6.dist-info/METADATA
streamlit_toggle_switch_aai-4.0.6.dist-info/WHEEL
streamlit_toggle_switch_aai-4.0.6.dist-info/top_level.txt
streamlit_toggle_switch_aai-4.0.6.dist-info/RECORD
