Metadata-Version: 2.1
Name: streamlit-toggle-switch-aai
Version: 4.0.6
Summary: Creates a customizable toggle
Home-page: https://github.com/sqlinsights/streamlit-toggle-switch
Author: Carlos D. Serrano
Author-email: sqlinsights@gmail.com
Requires-Python: >=3.6
License-File: LICENSE
Requires-Dist: streamlit (>=0.63)
